bodo_iceberg_connector/__init__.py
bodo_iceberg_connector/catalog_conn.py
bodo_iceberg_connector/errors.py
bodo_iceberg_connector/filter_to_java.py
bodo_iceberg_connector/java_helpers.py
bodo_iceberg_connector/parquet_info.py
bodo_iceberg_connector/py4j_support.py
bodo_iceberg_connector/write.py
bodo_iceberg_connector/jars/bodo-iceberg-reader.jar
bodo_iceberg_connector/jars/libs/HikariCP-2.6.1.jar
bodo_iceberg_connector/jars/libs/HikariCP-java7-2.4.12.jar
bodo_iceberg_connector/jars/libs/RoaringBitmap-1.0.1.jar
bodo_iceberg_connector/jars/libs/accessors-smart-2.4.7.jar
bodo_iceberg_connector/jars/libs/aircompressor-0.26.jar
bodo_iceberg_connector/jars/libs/annotations-2.29.26.jar
bodo_iceberg_connector/jars/libs/ant-1.9.1.jar
bodo_iceberg_connector/jars/libs/ant-launcher-1.9.1.jar
bodo_iceberg_connector/jars/libs/antlr-runtime-3.5.2.jar
bodo_iceberg_connector/jars/libs/aopalliance-1.0.jar
bodo_iceberg_connector/jars/libs/apache-client-2.29.26.jar
bodo_iceberg_connector/jars/libs/arns-2.29.26.jar
bodo_iceberg_connector/jars/libs/arrow-format-12.0.1.jar
bodo_iceberg_connector/jars/libs/arrow-memory-core-12.0.1.jar
bodo_iceberg_connector/jars/libs/arrow-memory-netty-15.0.0.jar
bodo_iceberg_connector/jars/libs/arrow-vector-12.0.1.jar
bodo_iceberg_connector/jars/libs/asm-9.1.jar
bodo_iceberg_connector/jars/libs/audience-annotations-0.5.0.jar
bodo_iceberg_connector/jars/libs/auth-2.29.26.jar
bodo_iceberg_connector/jars/libs/avro-1.11.3.jar
bodo_iceberg_connector/jars/libs/aws-core-2.29.26.jar
bodo_iceberg_connector/jars/libs/aws-java-sdk-core-1.12.382.jar
bodo_iceberg_connector/jars/libs/aws-java-sdk-dynamodb-1.12.382.jar
bodo_iceberg_connector/jars/libs/aws-java-sdk-kms-1.12.382.jar
bodo_iceberg_connector/jars/libs/aws-java-sdk-s3-1.12.382.jar
bodo_iceberg_connector/jars/libs/aws-java-sdk-sts-1.12.382.jar
bodo_iceberg_connector/jars/libs/aws-json-protocol-2.29.26.jar
bodo_iceberg_connector/jars/libs/aws-query-protocol-2.29.26.jar
bodo_iceberg_connector-2026.1.dist-info/METADATA
bodo_iceberg_connector-2026.1.dist-info/WHEEL
bodo_iceberg_connector-2026.1.dist-info/top_level.txt
bodo_iceberg_connector-2026.1.dist-info/RECORD
