Metadata-Version: 2.4
Name: bodo-iceberg-connector
Version: 2026.1
Summary: Bodo Connector for Iceberg
Author: Bodo.ai
Project-URL: Homepage, https://bodo.ai
Project-URL: Documentation, https://docs.bodo.ai
Keywords: data,analytics,cluster
Classifier: Development Status :: 5 - Production/Stable
Classifier: Intended Audience :: Developers
Classifier: Operating System :: POSIX :: Linux
Classifier: Programming Language :: Python
Classifier: Programming Language :: Python :: 3.10
Classifier: Programming Language :: Python :: 3.11
Classifier: Programming Language :: Python :: 3.12
Classifier: Programming Language :: Python :: 3.13
Classifier: Programming Language :: Python :: 3.14
Classifier: Topic :: Software Development :: Compilers
Classifier: Topic :: System :: Distributed Computing
Requires-Python: >=3.10
Requires-Dist: py4j==0.10.9.9
Requires-Dist: pyarrow==22.0.0
Requires-Dist: numpy>=1.24
Requires-Dist: pandas>=2.2
Requires-Dist: pyiceberg>=0.9
